icost/__init__.py
icost/__version__.py
icost/categorize_minority_v2.py
icost/icost.py
icost/mst_linked_ind.py
icost-0.1.1.dist-info/licenses/LICENSE.txt
icost-0.1.1.dist-info/METADATA
icost-0.1.1.dist-info/WHEEL
icost-0.1.1.dist-info/top_level.txt
icost-0.1.1.dist-info/RECORD
