Metadata-Version: 2.4
Name: icost
Version: 0.1.1
Summary: Instance-complexity based cost-sensitive learning
Author-email: Asif Newaz <eee.asifnewaz@iut-dhaka.edu>
License: MIT
Project-URL: Homepage, https://github.com/newaz-aa/icost
Project-URL: Issues, https://github.com/newaz-aa/icost/issues
Keywords: machine-learning,cost-sensitive learning,class-imbalance,scikit-learn
Classifier: Development Status :: 3 - Alpha
Classifier: Intended Audience :: Science/Research
Classifier: License :: OSI Approved :: MIT License
Classifier: Programming Language :: Python :: 3
Classifier: Topic :: Scientific/Engineering :: Artificial Intelligence
Requires-Python: >=3.8
License-File: LICENSE.txt
Requires-Dist: numpy>=1.21
Requires-Dist: pandas>=1.3
Requires-Dist: scikit-learn>=1.1
Dynamic: license-file
